{
	"archive" : {},
	"artifacts" : 
	[
		{
			"path" : "Engine/libengine.a"
		}
	],
	"backtrace" : 1,
	"backtraceGraph" : 
	{
		"commands" : 
		[
			"add_library",
			"target_compile_definitions",
			"include_directories",
			"target_include_directories"
		],
		"files" : 
		[
			"Engine/CMakeLists.txt"
		],
		"nodes" : 
		[
			{
				"file" : 0
			},
			{
				"command" : 0,
				"file" : 0,
				"line" : 9,
				"parent" : 0
			},
			{
				"command" : 1,
				"file" : 0,
				"line" : 13,
				"parent" : 0
			},
			{
				"command" : 2,
				"file" : 0,
				"line" : 3,
				"parent" : 0
			},
			{
				"command" : 3,
				"file" : 0,
				"line" : 11,
				"parent" : 0
			}
		]
	},
	"compileGroups" : 
	[
		{
			"compileCommandFragments" : 
			[
				{
					"fragment" : "-g"
				},
				{
					"fragment" : "-std=gnu++20"
				}
			],
			"defines" : 
			[
				{
					"backtrace" : 2,
					"define" : "ENGINE_VERSION=8"
				}
			],
			"includes" : 
			[
				{
					"backtrace" : 3,
					"path" : "C:/Users/96tho/Desktop/project/Engine/inlcude"
				},
				{
					"backtrace" : 3,
					"path" : "C:/Users/96tho/Desktop/project/Engine/headers"
				},
				{
					"backtrace" : 4,
					"path" : "C:/Users/96tho/Desktop/project/Engine/include"
				}
			],
			"language" : "CXX",
			"languageStandard" : 
			{
				"backtraces" : 
				[
					1
				],
				"standard" : "20"
			},
			"sourceIndexes" : 
			[
				0,
				1,
				2,
				3,
				4,
				5,
				6,
				7
			]
		}
	],
	"id" : "engine::@8f69bdd092c897d92c1e",
	"name" : "engine",
	"nameOnDisk" : "libengine.a",
	"paths" : 
	{
		"build" : "Engine",
		"source" : "Engine"
	},
	"sourceGroups" : 
	[
		{
			"name" : "Source Files",
			"sourceIndexes" : 
			[
				0,
				1,
				2,
				3,
				4,
				5,
				6,
				7
			]
		},
		{
			"name" : "Header Files",
			"sourceIndexes" : 
			[
				8,
				9,
				10,
				11,
				12,
				13,
				14,
				15,
				16,
				17,
				18
			]
		}
	],
	"sources" : 
	[
		{
			"backtrace" : 1,
			"compileGroupIndex" : 0,
			"path" : "Engine/src/FilterResults.cpp",
			"sourceGroupIndex" : 0
		},
		{
			"backtrace" : 1,
			"compileGroupIndex" : 0,
			"path" : "Engine/src/archetype.cpp",
			"sourceGroupIndex" : 0
		},
		{
			"backtrace" : 1,
			"compileGroupIndex" : 0,
			"path" : "Engine/src/component.cpp",
			"sourceGroupIndex" : 0
		},
		{
			"backtrace" : 1,
			"compileGroupIndex" : 0,
			"path" : "Engine/src/entity.cpp",
			"sourceGroupIndex" : 0
		},
		{
			"backtrace" : 1,
			"compileGroupIndex" : 0,
			"path" : "Engine/src/reflection.cpp",
			"sourceGroupIndex" : 0
		},
		{
			"backtrace" : 1,
			"compileGroupIndex" : 0,
			"path" : "Engine/src/spot.cpp",
			"sourceGroupIndex" : 0
		},
		{
			"backtrace" : 1,
			"compileGroupIndex" : 0,
			"path" : "Engine/src/table.cpp",
			"sourceGroupIndex" : 0
		},
		{
			"backtrace" : 1,
			"compileGroupIndex" : 0,
			"path" : "Engine/src/world.cpp",
			"sourceGroupIndex" : 0
		},
		{
			"backtrace" : 1,
			"path" : "Engine/include/FilterResults.hpp",
			"sourceGroupIndex" : 1
		},
		{
			"backtrace" : 1,
			"path" : "Engine/include/archetype.hpp",
			"sourceGroupIndex" : 1
		},
		{
			"backtrace" : 1,
			"path" : "Engine/include/component.hpp",
			"sourceGroupIndex" : 1
		},
		{
			"backtrace" : 1,
			"path" : "Engine/include/entity.hpp",
			"sourceGroupIndex" : 1
		},
		{
			"backtrace" : 1,
			"path" : "Engine/include/filter.hpp",
			"sourceGroupIndex" : 1
		},
		{
			"backtrace" : 1,
			"path" : "Engine/include/people.hpp",
			"sourceGroupIndex" : 1
		},
		{
			"backtrace" : 1,
			"path" : "Engine/include/reflection.hpp",
			"sourceGroupIndex" : 1
		},
		{
			"backtrace" : 1,
			"path" : "Engine/include/spot.hpp",
			"sourceGroupIndex" : 1
		},
		{
			"backtrace" : 1,
			"path" : "Engine/include/system.hpp",
			"sourceGroupIndex" : 1
		},
		{
			"backtrace" : 1,
			"path" : "Engine/include/table.hpp",
			"sourceGroupIndex" : 1
		},
		{
			"backtrace" : 1,
			"path" : "Engine/include/world.hpp",
			"sourceGroupIndex" : 1
		}
	],
	"type" : "STATIC_LIBRARY"
}
